fastapi_inferring_depends/__init__.py
fastapi_inferring_depends/depends.py
fastapi_inferring_depends/py.typed
fastapi_inferring_depends-1.0.0.post1.dist-info/LICENSE
fastapi_inferring_depends-1.0.0.post1.dist-info/METADATA
fastapi_inferring_depends-1.0.0.post1.dist-info/WHEEL
fastapi_inferring_depends-1.0.0.post1.dist-info/RECORD
