Metadata-Version: 2.1
Name: fastapi-inferring-depends
Version: 1.0.0.post1
Summary: A wrapper around FastAPI's Depends function that infers its return type from its input
Home-page: https://github.com/jvllmr/fastapi-inferring-depends
License: MIT
Author: Jan Vollmer
Author-email: jan@vllmr.dev
Requires-Python: >=3.7,<4.0
Classifier: License :: OSI Approved :: MIT License
Classifier: Programming Language :: Python :: 3
Classifier: Programming Language :: Python :: 3.7
Classifier: Programming Language :: Python :: 3.8
Classifier: Programming Language :: Python :: 3.9
Classifier: Programming Language :: Python :: 3.10
Classifier: Programming Language :: Python :: 3.11
Requires-Dist: fastapi
Project-URL: Repository, https://github.com/jvllmr/fastapi-inferring-depends
